parboil/__init__.py
parboil/__main__.py
parboil/console.py
parboil/errors.py
parboil/ext.py
parboil/helpers.py
parboil/ingredients.py
parboil/parboil.py
parboil/recipes.py
parboil/renderer.py
parboil/settings.py
parboil/tasks.py
parboil-0.9.3.dist-info/LICENSE
parboil-0.9.3.dist-info/METADATA
parboil-0.9.3.dist-info/WHEEL
parboil-0.9.3.dist-info/entry_points.txt
parboil-0.9.3.dist-info/RECORD
