Metadata-Version: 2.1
Name: parboil
Version: 0.9.3
Summary: Create reusable boilerplate templates to kickstart your next project.
Home-page: http://github.com/jneug/parboil
License: MIT
Author: J. Neugebauer
Author-email: github@neugebauer.cc
Requires-Python: >=3.9,<4.0
Classifier: License :: OSI Approved :: MIT License
Classifier: Operating System :: MacOS
Classifier: Operating System :: POSIX
Classifier: Operating System :: Unix
Classifier: Programming Language :: Python :: 3
Classifier: Programming Language :: Python :: 3.9
Classifier: Programming Language :: Python :: 3.10
Classifier: Programming Language :: Python :: 3.11
Classifier: Programming Language :: Python :: 3.12
Requires-Dist: Jinja2 (>=3.0.2,<4.0.0)
Requires-Dist: click (>=8.0.3,<9.0.0)
Requires-Dist: jinja2-ansible-filters (>=1.3.2,<2.0.0)
Requires-Dist: jsoncparser (>=1.0.4,<2.0.0)
Requires-Dist: rich (>=12.6.0,<13.0.0)
Project-URL: Repository, http://github.com/jneug/parboil
